max_portal_gun/__init__.py
max_portal_gun/main.py
max_portal_gun-0.1.0.dist-info/METADATA
max_portal_gun-0.1.0.dist-info/WHEEL
max_portal_gun-0.1.0.dist-info/entry_points.txt
max_portal_gun-0.1.0.dist-info/RECORD
